NutriCheck/Snakefile
NutriCheck/__init__.py
NutriCheck/classe_gene.py
NutriCheck/classe_organisme.py
NutriCheck/main_toxico.py
NutriCheck/purine_module.py
NutriCheck/tools_toxico.py
nutricheck-0.1.5.dist-info/METADATA
nutricheck-0.1.5.dist-info/WHEEL
nutricheck-0.1.5.dist-info/RECORD
